liberation_direct/__init__.py
liberation_direct-1.0.2.dist-info/LICENSE
liberation_direct-1.0.2.dist-info/METADATA
liberation_direct-1.0.2.dist-info/WHEEL
liberation_direct-1.0.2.dist-info/top_level.txt
liberation_direct-1.0.2.dist-info/RECORD
