Metadata-Version: 2.1
Name: liberation-direct
Version: 1.0.2
Summary: Parse Libération's live news page.
Home-page: https://github.com/massoncl/liberation-direct
Author: Clément Masson
License: MIT
Platform: UNKNOWN
Classifier: License :: OSI Approved :: MIT License
Classifier: Programming Language :: Python :: 3
Classifier: Programming Language :: Python :: 3.8
Requires-Dist: beautifulsoup4
Requires-Dist: markdownify
